setup.cfg
setup.py
wd-entities
wd_entities
wd_entities/__init__.py
wd_entities/api.py
wd_entities/metadata.json
wd_entities.egg-info/PKG-INFO
wd_entities.egg-info/SOURCES.txt
wd_entities.egg-info/dependency_links.txt
wd_entities.egg-info/requires.txt
wd_entities.egg-info/top_level.txt