Metadata-Version: 1.1
Name: wd-entities
Version: 0.1.10
Summary: A REST API wrapper for Wikidata entities
Home-page: https://github.com/fserena/wd-entities
Author: Fernando Serena
Author-email: fserena@fi.upm.es
License: Apache 2
Download-URL: https://github.com/fserena/wd-entities/tarball/0.1.10
Keywords: overpass,osm
Platform: UNKNOWN
